rbac/__init__.py
py_rbac-20.12.3.dist-info/LICENSE
py_rbac-20.12.3.dist-info/METADATA
py_rbac-20.12.3.dist-info/WHEEL
py_rbac-20.12.3.dist-info/top_level.txt
py_rbac-20.12.3.dist-info/RECORD
