Metadata-Version: 2.1
Name: py-rbac
Version: 20.12.3
Summary: Python implementation of the NIST model for role based access control (RBAC).
Home-page: https://github.com/muratgozel/py-rbac
Author: Murat Gözel
Author-email: murat@gozel.com.tr
License: UNKNOWN
Project-URL: Source, https://github.com/muratgozel/py-rbac
Project-URL: Documentation, https://github.com/muratgozel/py-rbac
Project-URL: Bug Reports, https://github.com/muratgozel/py-rbac/issues
Project-URL: Funding, https://ko-fi.com/muratgozel
Keywords: rbac,access control,role based access control
Platform: UNKNOWN
Classifier: Intended Audience :: Developers
Classifier: License :: OSI Approved :: MIT License
Classifier: Natural Language :: English
Classifier: Operating System :: MacOS :: MacOS X
Classifier: Operating System :: POSIX
Classifier: Operating System :: POSIX :: BSD
Classifier: Operating System :: POSIX :: Linux
Classifier: Operating System :: Microsoft :: Windows
Classifier: Programming Language :: Python
Classifier: Programming Language :: Python :: 3
Classifier: Programming Language :: Python :: 3 :: Only
Classifier: Programming Language :: Python :: 3.6
Classifier: Programming Language :: Python :: 3.7
Classifier: Programming Language :: Python :: 3.8
Classifier: Programming Language :: Python :: 3.9
